django_ldap3_auth/__init__.py
django_ldap3_auth/admin.py
django_ldap3_auth/apps.py
django_ldap3_auth/backends.py
django_ldap3_auth/conf.py
django_ldap3_auth/forms.py
django_ldap3_auth/models.py
django_ldap3_auth/settings.py
django_ldap3_auth/management/__init__.py
django_ldap3_auth/management/__pycache__/__init__.cpython-313.pyc
django_ldap3_auth/management/commands/__init__.py
django_ldap3_auth/management/commands/ldap_test.py
django_ldap3_auth/management/commands/__pycache__/__init__.cpython-313.pyc
django_ldap3_auth/management/commands/__pycache__/ldap_test.cpython-313.pyc
django_ldap3_auth/migrations/0001_initial.py
django_ldap3_auth/migrations/__init__.py
django_ldap3_auth/static/django_ldap3_auth/ldapconfig.js
django_ldap3_auth/utils/__init__.py
django_ldap3_auth/utils/ldap.py
django_ldap3_auth-0.1.0.dist-info/METADATA
django_ldap3_auth-0.1.0.dist-info/WHEEL
django_ldap3_auth-0.1.0.dist-info/top_level.txt
django_ldap3_auth-0.1.0.dist-info/RECORD
