Metadata-Version: 2.4
Name: django-ldap3-auth
Version: 0.1.0
Summary: Django authentication backend for Active Directory/LDAP via ldap3 with optional admin-configurable settings.
Author-email: akula993 <akula993@gmail.com>
License: MIT
Project-URL: Homepage, https://github.com/akula993/django_ldap3_auth
Requires-Python: >=3.10
Requires-Dist: Django>=4.2
Requires-Dist: ldap3>=2.9
